Metadata-Version: 2.4
Name: aicourse_dist_prob_asreeman
Version: 1.4
Summary: Gaussian and Binomial Distributions
Author: Arjun Sree Manoj
Author-email: rjsree66@gmail.com
Dynamic: author
Dynamic: author-email
Dynamic: description
Dynamic: description-content-type
Dynamic: summary
